{
  "stock": [
    {
      "id": 1,
      "amount": 3
    },
    {
      "id": 2,
      "amount": 5
    },
    {
      "id": 3,
      "amount": 2
    },
    {
      "id": 4,
      "amount": 1
    },
    {
      "id": 5,
      "amount": 5
    },
    {
      "id": 6,
      "amount": 10
    }
  ],
  "products": [
    {
      "id": 1,
      "title": "Tênis de Caminhada Leve  muito Confortável Confortável",
      "price": 139.9,
      "image": "https://images.unsplash.com/photo-1548512870-345e464c7ad2?ixlib=rb-1.2.1&ixid=eyJhcHBfaWQiOjEyMDd9&auto=format&fit=crop&w=1050&q=80"
    },
    {
      "id": 2,
      "title": "Tênis VR Caminhada Confortável Detalhes Couro Masculino",
      "price": 111.9,
      "image": "https://images.unsplash.com/photo-1527128296579-fce16948f060?ixlib=rb-1.2.1&auto=format&fit=crop&w=1050&q=80"
    },
    {
      "id": 3,
      "title": "Tênis Adidas Duramo Lite 2.0",
      "price": 119.9,
      "image": "https://images.unsplash.com/photo-1542280756-74b2f55e73ab?ixlib=rb-1.2.1&auto=format&fit=crop&w=1050&q=80"
    },
    {
      "id": 5,
      "title": "Tênis VR Caminhada Confortável Detalhes Couro Masculino",
      "price": 100.9,
      "image": "https://images.unsplash.com/photo-1556048219-bb6978360b84?ixlib=rb-1.2.1&auto=format&fit=crop&w=1051&q=80"
    },
    {
      "id": 6,
      "title": "Tênis Adidas Duramo Lite 2.0",
      "price": 223.9,
      "image": "https://images.unsplash.com/photo-1432712641917-22ce322ab531?ixlib=rb-1.2.1&auto=format&fit=crop&w=967&q=80"
    },
    {
      "id": 4,
      "title": "Tênis de Caminhada Leve Confortável",
      "price": 122.9,
      "image": "https://images.unsplash.com/photo-1559304022-afbf28f53c4d?ixlib=rb-1.2.1&auto=format&fit=crop&w=1056&q=80"
    }
  ]
}
